skyhookintel/__init__.py
skyhookintel/admin.py
skyhookintel/app_settings.py
skyhookintel/apps.py
skyhookintel/auth_hooks.py
skyhookintel/models.py
skyhookintel/regex.py
skyhookintel/tasks.py
skyhookintel/urls.py
skyhookintel/views.py
skyhookintel/locale/en/LC_MESSAGES/django.mo
skyhookintel/locale/en/LC_MESSAGES/django.po
skyhookintel/management/commands/skyhook_intel_create_constellation.py
skyhookintel/management/commands/skyhook_intel_create_region.py
skyhookintel/migrations/0001_initial.py
skyhookintel/migrations/0002_alter_general_options.py
skyhookintel/migrations/__init__.py
skyhookintel/templates/skyhookintel/add_timer.html
skyhookintel/templates/skyhookintel/base.html
skyhookintel/templates/skyhookintel/close_page.html
skyhookintel/templates/skyhookintel/no_timers.html
skyhookintel/templates/skyhookintel/upcoming.html
skyhookintel/templates/skyhookintel/partials/global_js.html
skyhookintel/templates/skyhookintel/partials/menu.html
skyhookintel/tests/__init__.py
skyhookintel/tests/test_regex.py
skyhookintel/tests/test_skyhook.py
skyhookintel/tests/testdata/README.md
skyhookintel/tests/testdata/__init__.py
skyhookintel/tests/testdata/create_eveuniverse.py
skyhookintel/tests/testdata/eveuniverse.json
skyhookintel/tests/testdata/load_eveuniverse.py
aa_skyhook_intel-0.1.1.dist-info/LICENSE
aa_skyhook_intel-0.1.1.dist-info/WHEEL
aa_skyhook_intel-0.1.1.dist-info/METADATA
aa_skyhook_intel-0.1.1.dist-info/RECORD
